pip_box/__init__.py
pip_box/dependencies_base.py
pip_box/main.py
pip_box/tool.py
pip_box/utils.py
pip_box/version_checker.py
pip_box-0.4.5.dist-info/LICENSE
pip_box-0.4.5.dist-info/METADATA
pip_box-0.4.5.dist-info/WHEEL
pip_box-0.4.5.dist-info/entry_points.txt
pip_box-0.4.5.dist-info/top_level.txt
pip_box-0.4.5.dist-info/RECORD
