Metadata-Version: 2.1
Name: pip-box
Version: 0.4.5
Summary: An easy tool for upgrading all of your packages while not breaking dependencies
Home-page: https://github.com/realiti4/pip-upgrade
Author: Onur Cetinkol
Author-email: realiti44@gmail.com
License: UNKNOWN
Platform: UNKNOWN
Classifier: Programming Language :: Python :: 3
Classifier: License :: OSI Approved :: MIT License
Classifier: Operating System :: OS Independent
Requires-Python: >=3.6
Requires-Dist: packaging
